bodytracking/__init__.py
bodytracking-1.6.dist-info/METADATA
bodytracking-1.6.dist-info/WHEEL
bodytracking-1.6.dist-info/license
bodytracking-1.6.dist-info/top_level.txt
bodytracking-1.6.dist-info/RECORD
