Metadata-Version: 2.1
Name: bodytracking
Version: 1.6
Summary: bodytracking is a collection of functions powered by mediapipe and opencv-python.
Home-page: https://github.com/MOBSkuchen/tkt-Toolkit
Author: Suprime
Author-email: suprime.sendings@gmail.com
License: MIT
Platform: UNKNOWN
Classifier: Programming Language :: Python :: 3
Classifier: License :: OSI Approved :: MIT License
Classifier: Operating System :: OS Independent
Requires-Python: >=3.7
License-File: license
Requires-Dist: mediapipe
Requires-Dist: opencv-python
